.gitignore
CHANGES.txt
MANIFEST.in
README.rst
bootstrap.py
buildout.cfg
setup.py
collective/__init__.py
collective.randomcontent.egg-info/PKG-INFO
collective.randomcontent.egg-info/SOURCES.txt
collective.randomcontent.egg-info/dependency_links.txt
collective.randomcontent.egg-info/entry_points.txt
collective.randomcontent.egg-info/namespace_packages.txt
collective.randomcontent.egg-info/not-zip-safe
collective.randomcontent.egg-info/requires.txt
collective.randomcontent.egg-info/top_level.txt
collective/randomcontent/__init__.py
collective/randomcontent/browser.py
collective/randomcontent/configure.zcml
collective/randomcontent/interfaces.py
collective/randomcontent/settings.py
collective/randomcontent/testing.py
collective/randomcontent/update_locales.sh
collective/randomcontent/locales/collective.randomcontent.pot
collective/randomcontent/locales/manual.pot
collective/randomcontent/locales/en/LC_MESSAGES/collective.randomcontent.mo
collective/randomcontent/locales/en/LC_MESSAGES/collective.randomcontent.po
collective/randomcontent/locales/nl/LC_MESSAGES/collective.randomcontent.mo
collective/randomcontent/locales/nl/LC_MESSAGES/collective.randomcontent.po
collective/randomcontent/profiles/default/controlpanel.xml
collective/randomcontent/profiles/default/metadata.xml
collective/randomcontent/profiles/default/registry.xml
collective/randomcontent/tests/__init__.py
collective/randomcontent/tests/test_functional.py
docs/LICENSE.GPL
docs/LICENSE.txt