Metadata-Version: 1.0
Name: collective.randomcontent
Version: 1.0
Summary: Redirect to random content, especially images.
Home-page: https://github.com/collective/collective.randomcontent
Author: Maurits van Rees
Author-email: m.van.rees@zestsoftware.nl
License: GPL
Platform: UNKNOWN
Classifier: Programming Language :: Python
Classifier: Framework :: Plone
Classifier: Framework :: Plone :: 4.0
Classifier: Framework :: Plone :: 4.1
Classifier: Framework :: Plone :: 4.2
